Workbook
Name Slicer_Region: #N/A
Name Slicer_Segment: #N/A
Name Slicer_Year: #N/A

Sheet Data
A1: Customer Name | B1: Order ID | C1: Year | D1: Order Date | E1: Ship Date | F1: Ship Mode | G1: Customer ID | H1: Segment | I1: Country | J1: City | K1: State | L1: Postal Code | M1: Region | N1: Product ID | O1: Category | P1: Sub-Category | Q1: Sales | R1: Quantity | S1: Discount | T1: Profit
A2: Claire Gute | B2: CA-2013-152156 | C2: =YEAR(Data!$D2) -> 2013 | D2: 41587 | E2: 41590 | F2: Second Class | G2: CG-12520 | H2: Consumer | I2: United States | J2: Henderson | K2: Kentucky | L2: 42420 | M2: South | N2: FUR-BO-10001798 | O2: Furniture | P2: Bookcases | Q2: 261.96 | R2: 2 | S2: 0 | T2: 41.9136
A3: Darrin Van Huff | B3: CA-2013-138688 | C3: =YEAR(Data!$D4) -> 2012 | D3: 41438 | E3: 41442 | F3: Second Class | G3: DV-13045 | H3: Corporate | I3: United States | J3: Los Angeles | K3: California | L3: 90036 | M3: West | N3: OFF-LA-10000240 | O3: Office Supplies | P3: Labels | Q3: 14.62 | R3: 2 | S3: 0 | T3: 6.8714
A4: Sean O'Donnell | B4: US-2012-108966 | C4: =YEAR(Data!$D5) -> 2011 | D4: 41193 | E4: 41200 | F4: Standard Class | G4: SO-20335 | H4: Consumer | I4: United States | J4: Fort Lauderdale | K4: Florida | L4: 33311 | M4: South | N4: FUR-TA-10000577 | O4: Furniture | P4: Tables | Q4: 957.5775 | R4: 5 | S4: 0.45 | T4: -383.031
A5: Brosina Hoffman | B5: CA-2011-115812 | C5: =YEAR(Data!$D7) -> 2013 | D5: 40703 | E5: 40708 | F5: Standard Class | G5: BH-11710 | H5: Consumer | I5: United States | J5: Los Angeles | K5: California | L5: 90032 | M5: West | N5: FUR-FU-10001487 | O5: Furniture | P5: Furnishings | Q5: 48.86 | R5: 7 | S5: 0 | T5: 14.1694
A6: Andrew Allen | B6: CA-2014-114412 | C6: =YEAR(Data!$D14) -> 2012 | D6: 41745 | E6: 41750 | F6: Standard Class | G6: AA-10480 | H6: Consumer | I6: United States | J6: Concord | K6: North Carolina | L6: 28027 | M6: South | N6: OFF-PA-10002365 | O6: Office Supplies | P6: Paper | Q6: 15.552 | R6: 3 | S6: 0.2 | T6: 5.4432
A7: Irene Maddox | B7: CA-2013-161389 | C7: =YEAR(Data!$D15) -> 2013 | D7: 41614 | E7: 41619 | F7: Standard Class | G7: IM-15070 | H7: Consumer | I7: United States | J7: Seattle | K7: Washington | L7: 98103 | M7: West | N7: OFF-BI-10003656 | O7: Office Supplies | P7: Binders | Q7: 407.976 | R7: 3 | S7: 0.2 | T7: 132.5922
A8: Harold Pawlan | B8: US-2012-118983 | C8: =YEAR(Data!$D16) -> 2012 | D8: 41235 | E8: 41239 | F8: Standard Class | G8: HP-14815 | H8: Home Office | I8: United States | J8: Fort Worth | K8: Texas | L8: 76106 | M8: Central | N8: OFF-AP-10002311 | O8: Office Supplies | P8: Appliances | Q8: 68.81 | R8: 5 | S8: 0.8 | T8: -123.858
A9: Pete Kriz | B9: CA-2011-105893 | C9: =YEAR(Data!$D18) -> 2013 | D9: 40858 | E9: 40865 | F9: Standard Class | G9: PK-19075 | H9: Consumer | I9: United States | J9: Madison | K9: Wisconsin | L9: 53711 | M9: Central | N9: OFF-ST-10004186 | O9: Office Supplies | P9: Storage | Q9: 665.88 | R9: 6 | S9: 0 | T9: 13.3176
A10: Alejandro Grove | B10: CA-2011-167164 | C10: =YEAR(Data!$D19) -> 2012 | D10: 40676 | E10: 40678 | F10: Second Class | G10: AG-10270 | H10: Consumer | I10: United States | J10: West Jordan | K10: Utah | L10: 84084 | M10: West | N10: OFF-ST-10000107 | O10: Office Supplies | P10: Storage | Q10: 55.5 | R10: 2 | S10: 0 | T10: 9.99
A11: Zuschuss Donatelli | B11: CA-2011-143336 | C11: =YEAR(Data!$D20) -> 2014 | D11: 40782 | E11: 40787 | F11: Second Class | G11: ZD-21925 | H11: Consumer | I11: United States | J11: San Francisco | K11: California | L11: 94109 | M11: West | N11: OFF-AR-10003056 | O11: Office Supplies | P11: Art | Q11: 8.56 | R11: 2 | S11: 0 | T11: 2.4824
A12: Ken Black | B12: CA-2013-137330 | C12: =YEAR(Data!$D23) -> 2013 | D12: 41618 | E12: 41622 | F12: Standard Class | G12: KB-16585 | H12: Corporate | I12: United States | J12: Fremont | K12: Nebraska | L12: 68025 | M12: Central | N12: OFF-AR-10000246 | O12: Office Supplies | P12: Art | Q12: 19.46 | R12: 7 | S12: 0 | T12: 5.0596
A13: Sandra Flanagan | B13: US-2014-156909 | C13: =YEAR(Data!$D25) -> 2013 | D13: 41837 | E13: 41839 | F13: Second Class | G13: SF-20065 | H13: Consumer | I13: United States | J13: Philadelphia | K13: Pennsylvania | L13: 19140 | M13: East | N13: FUR-CH-10002774 | O13: Furniture | P13: Chairs | Q13: 71.372 | R13: 2 | S13: 0.3 | T13: -1.0196
A14: Emily Burns | B14: CA-2012-106320 | C14: =YEAR(Data!$D26) -> 2012 | D14: 41177 | E14: 41182 | F14: Standard Class | G14: EB-13870 | H14: Consumer | I14: United States | J14: Orem | K14: Utah | L14: 84057 | M14: West | N14: FUR-TA-10000577 | O14: Furniture | P14: Tables | Q14: 1044.63 | R14: 3 | S14: 0 | T14: 240.2649
A15: Eric Hoffmann | B15: CA-2013-121755 | C15: =YEAR(Data!$D27) -> 2013 | D15: 41290 | E15: 41294 | F15: Second Class | G15: EH-13945 | H15: Consumer | I15: United States | J15: Los Angeles | K15: California | L15: 90049 | M15: West | N15: OFF-BI-10001634 | O15: Office Supplies | P15: Binders | Q15: 11.648 | R15: 2 | S15: 0.2 | T15: 4.2224
A16: Tracy Blumstein | B16: US-2012-150630 | C16: =YEAR(Data!$D29) -> 2012 | D16: 41169 | E16: 41173 | F16: Standard Class | G16: TB-21520 | H16: Consumer | I16: United States | J16: Philadelphia | K16: Pennsylvania | L16: 19140 | M16: East | N16: FUR-BO-10004834 | O16: Furniture | P16: Bookcases | Q16: 3083.43 | R16: 7 | S16: 0.5 | T16: -1665.0522
A17: Matt Abelman | B17: CA-2014-107727 | C17: =YEAR(Data!$D36) -> 2014 | D17: 41932 | E17: 41936 | F17: Second Class | G17: MA-17560 | H17: Home Office | I17: United States | J17: Houston | K17: Texas | L17: 77095 | M17: Central | N17: OFF-PA-10000249 | O17: Office Supplies | P17: Paper | Q17: 29.472 | R17: 3 | S17: 0.2 | T17: 9.9468
A18: Gene Hale | B18: CA-2013-117590 | C18: =YEAR(Data!$D37) -> 2011 | D18: 41617 | E18: 41619 | F18: First Class | G18: GH-14485 | H18: Corporate | I18: United States | J18: Richardson | K18: Texas | L18: 75080 | M18: Central | N18: TEC-PH-10004977 | O18: Technology | P18: Phones | Q18: 1097.544 | R18: 7 | S18: 0.2 | T18: 123.4737
A19: Steve Nguyen | B19: CA-2012-117415 | C19: =YEAR(Data!$D39) -> 2011 | D19: 41270 | E19: 41274 | F19: Standard Class | G19: SN-20710 | H19: Home Office | I19: United States | J19: Houston | K19: Texas | L19: 77041 | M19: Central | N19: OFF-EN-10002986 | O19: Office Supplies | P19: Envelopes | Q19: 113.328 | R19: 9 | S19: 0.2 | T19: 35.415
A20: Linda Cazamias | B20: CA-2014-120999 | C20: =YEAR(Data!$D43) -> 2014 | D20: 41893 | E20: 41898 | F20: Standard Class | G20: LC-16930 | H20: Corporate | I20: United States | J20: Naperville | K20: Illinois | L20: 60540 | M20: Central | N20: TEC-PH-10004093 | O20: Technology | P20: Phones | Q20: 147.168 | R20: 4 | S20: 0.2 | T20: 16.5564
A21: Ruben Ausman | B21: CA-2013-101343 | C21: =YEAR(Data!$D44) -> 2013 | D21: 41473 | E21: 41478 | F21: Standard Class | G21: RA-19885 | H21: Corporate | I21: United States | J21: Los Angeles | K21: California | L21: 90049 | M21: West | N21: OFF-ST-10003479 | O21: Office Supplies | P21: Storage | Q21: 77.88 | R21: 2 | S21: 0 | T21: 3.894
A22: Erin Smith | B22: CA-2014-139619 | C22: =YEAR(Data!$D45) -> 2013 | D22: 41902 | E22: 41906 | F22: Standard Class | G22: ES-14080 | H22: Corporate | I22: United States | J22: Melbourne | K22: Florida | L22: 32935 | M22: South | N22: OFF-ST-10003282 | O22: Office Supplies | P22: Storage | Q22: 95.616 | R22: 2 | S22: 0.2 | T22: 9.5616
A23: Odella Nelson | B23: CA-2013-118255 | C23: =YEAR(Data!$D46) -> 2012 | D23: 41345 | E23: 41347 | F23: First Class | G23: ON-18715 | H23: Corporate | I23: United States | J23: Eagan | K23: Minnesota | L23: 55122 | M23: Central | N23: TEC-AC-10000171 | O23: Technology | P23: Accessories | Q23: 45.98 | R23: 2 | S23: 0 | T23: 19.7714
A24: Patrick O'Donnell | B24: CA-2011-146703 | C24: =YEAR(Data!$D48) -> 2014 | D24: 40836 | E24: 40841 | F24: Second Class | G24: PO-18865 | H24: Consumer | I24: United States | J24: Westland | K24: Michigan | L24: 48185 | M24: Central | N24: OFF-ST-10001713 | O24: Office Supplies | P24: Storage | Q24: 211.96 | R24: 4 | S24: 0 | T24: 8.4784
A25: Lena Hernandez | B25: CA-2013-169194 | C25: =YEAR(Data!$D49) -> 2014 | D25: 41446 | E25: 41451 | F25: Standard Class | G25: LH-16900 | H25: Consumer | I25: United States | J25: Dover | K25: Delaware | L25: 19901 | M25: East | N25: TEC-AC-10002167 | O25: Technology | P25: Accessories | Q25: 45 | R25: 3 | S25: 0 | T25: 4.95
A26: Darren Powers | B26: CA-2012-115742 | C26: =YEAR(Data!$D51) -> 2013 | D26: 41017 | E26: 41021 | F26: Standard Class | G26: DP-13000 | H26: Consumer | I26: United States | J26: New Albany | K26: Indiana | L26: 47150 | M26: Central | N26: OFF-BI-10004410 | O26: Office Supplies | P26: Binders | Q26: 38.22 | R26: 6 | S26: 0 | T26: 17.9634
A27: Janet Molinari | B27: CA-2013-105816 | C27: =YEAR(Data!$D55) -> 2012 | D27: 41620 | E27: 41626 | F27: Standard Class | G27: JM-15265 | H27: Corporate | I27: United States | J27: New York City | K27: New York | L27: 10024 | M27: East | N27: OFF-FA-10000304 | O27: Office Supplies | P27: Fasteners | Q27: 15.26 | R27: 7 | S27: 0 | T27: 6.2566
A28: Ted Butterfield | B28: CA-2013-111682 | C28: =YEAR(Data!$D57) -> 2013 | D28: 41443 | E28: 41444 | F28: First Class | G28: TB-21055 | H28: Consumer | I28: United States | J28: Troy | K28: New York | L28: 12180 | M28: East | N28: OFF-ST-10000604 | O28: Office Supplies | P28: Storage | Q28: 208.56 | R28: 6 | S28: 0 | T28: 52.14
A29: Kunst Miller | B29: CA-2012-135545 | C29: =YEAR(Data!$D64) -> 2014 | D29: 41237 | E29: 41243 | F29: Standard Class | G29: KM-16720 | H29: Consumer | I29: United States | J29: Los Angeles | K29: California | L29: 90004 | M29: West | N29: TEC-AC-10004633 | O29: Technology | P29: Accessories | Q29: 13.98 | R29: 2 | S29: 0 | T29: 6.1512
A30: Paul Stevenson | B30: US-2012-164175 | C30: =YEAR(Data!$D68) -> 2013 | D30: 41029 | E30: 41034 | F30: Standard Class | G30: PS-18970 | H30: Home Office | I30: United States | J30: Chicago | K30: Illinois | L30: 60610 | M30: Central | N30: FUR-CH-10001146 | O30: Furniture | P30: Chairs | Q30: 213.115 | R30: 5 | S30: 0.3 | T30: -15.2225
A31: Brendan Sweed | B31: CA-2011-106376 | C31: =YEAR(Data!$D69) -> 2014 | D31: 40882 | E31: 40887 | F31: Standard Class | G31: BS-11590 | H31: Corporate | I31: United States | J31: Gilbert | K31: Arizona | L31: 85234 | M31: West | N31: OFF-AR-10002671 | O31: Office Supplies | P31: Art | Q31: 1113.024 | R31: 8 | S31: 0.2 | T31: 111.3024
A32: Karen Daniels | B32: CA-2013-119823 | C32: =YEAR(Data!$D71) -> 2012 | D32: 41430 | E32: 41432 | F32: First Class | G32: KD-16270 | H32: Consumer | I32: United States | J32: Springfield | K32: Virginia | L32: 22153 | M32: South | N32: OFF-PA-10000482 | O32: Office Supplies | P32: Paper | Q32: 75.88 | R32: 2 | S32: 0 | T32: 35.6636
A33: Henry MacAllister | B33: CA-2013-106075 | C33: =YEAR(Data!$D72) -> 2011 | D33: 41536 | E33: 41541 | F33: Standard Class | G33: HM-14980 | H33: Consumer | I33: United States | J33: New York City | K33: New York | L33: 10009 | M33: East | N33: OFF-BI-10004654 | O33: Office Supplies | P33: Binders | Q33: 4.616 | R33: 1 | S33: 0.2 | T33: 1.731
A34: Tracy Blumstein | B34: CA-2014-114440 | C34: =YEAR(Data!$D73) -> 2013 | D34: 41897 | E34: 41900 | F34: Second Class | G34: TB-21520 | H34: Consumer | I34: United States | J34: Jackson | K34: Michigan | L34: 49201 | M34: Central | N34: OFF-PA-10004675 | O34: Office Supplies | P34: Paper | Q34: 19.05 | R34: 3 | S34: 0 | T34: 8.763
A35: Joel Eaton | B35: US-2012-134026 | C35: =YEAR(Data!$D74) -> 2013 | D35: 41025 | E35: 41031 | F35: Standard Class | G35: JE-15745 | H35: Consumer | I35: United States | J35: Memphis | K35: Tennessee | L35: 38109 | M35: South | N35: FUR-CH-10000513 | O35: Furniture | P35: Chairs | Q35: 831.936 | R35: 8 | S35: 0.2 | T35: -114.3912
A36: Ken Brennan | B36: US-2014-118038 | C36: =YEAR(Data!$D77) -> 2011 | D36: 41983 | E36: 41985 | F36: First Class | G36: KB-16600 | H36: Corporate | I36: United States | J36: Houston | K36: Texas | L36: 77041 | M36: Central | N36: OFF-BI-10004182 | O36: Office Supplies | P36: Binders | Q36: 1.248 | R36: 3 | S36: 0.8 | T36: -1.9344
A37: Joel Eaton | B37: US-2011-147606 | C37: =YEAR(Data!$D80) -> 2012 | D37: 40873 | E37: 40878 | F37: Second Class | G37: JE-15745 | H37: Consumer | I37: United States | J37: Houston | K37: Texas | L37: 77070 | M37: Central | N37: FUR-FU-10003194 | O37: Furniture | P37: Furnishings | Q37: 19.3 | R37: 5 | S37: 0.6 | T37: -14.475
A38: Stewart Carmichael | B38: CA-2013-127208 | C38: =YEAR(Data!$D81) -> 2013 | D38: 41438 | E38: 41441 | F38: First Class | G38: SC-20770 | H38: Corporate | I38: United States | J38: Decatur | K38: Alabama | L38: 35601 | M38: South | N38: OFF-AP-10002118 | O38: Office Supplies | P38: Appliances | Q38: 208.16 | R38: 1 | S38: 0 | T38: 56.2032
A39: Duane Noonan | B39: CA-2011-139451 | C39: =YEAR(Data!$D83) -> 2011 | D39: 40828 | E39: 40832 | F39: Standard Class | G39: DN-13690 | H39: Consumer | I39: United States | J39: San Francisco | K39: California | L39: 94122 | M39: West | N39: OFF-AR-10002053 | O39: Office Supplies | P39: Art | Q39: 14.9 | R39: 5 | S39: 0 | T39: 4.172
A40: Julie Creighton | B40: CA-2012-149734 | C40: =YEAR(Data!$D85) -> 2011 | D40: 41155 | E40: 41160 | F40: Standard Class | G40: JC-16105 | H40: Corporate | I40: United States | J40: Durham | K40: North Carolina | L40: 27707 | M40: South | N40: OFF-EN-10000927 | O40: Office Supplies | P40: Envelopes | Q40: 200.984 | R40: 7 | S40: 0.2 | T40: 62.8075
A41: Christopher Schild | B41: US-2014-119662 | C41: =YEAR(Data!$D86) -> 2014 | D41: 41957 | E41: 41960 | F41: First Class | G41: CS-12400 | H41: Home Office | I41: United States | J41: Chicago | K41: Illinois | L41: 60623 | M41: Central | N41: OFF-ST-10003656 | O41: Office Supplies | P41: Storage | Q41: 230.376 | R41: 3 | S41: 0.2 | T41: -48.9549
A42: Patrick O'Donnell | B42: CA-2014-140088 | C42: =YEAR(Data!$D87) -> 2012 | D42: 41788 | E42: 41790 | F42: Second Class | G42: PO-18865 | H42: Consumer | I42: United States | J42: Columbia | K42: South Carolina | L42: 29203 | M42: South | N42: FUR-CH-10000863 | O42: Furniture | P42: Chairs | Q42: 301.96 | R42: 2 | S42: 0 | T42: 33.2156
A43: Paul Gonzalez | B43: CA-2014-155558 | C43: =YEAR(Data!$D88) -> 2012 | D43: 41939 | E43: 41946 | F43: Standard Class | G43: PG-18895 | H43: Consumer | I43: United States | J43: Rochester | K43: Minnesota | L43: 55901 | M43: Central | N43: TEC-AC-10001998 | O43: Technology | P43: Accessories | Q43: 19.99 | R43: 1 | S43: 0 | T43: 6.7966
A44: Gary Mitchum | B44: CA-2013-159695 | C44: =YEAR(Data!$D90) -> 2011 | D44: 41370 | E44: 41375 | F44: Second Class | G44: GM-14455 | H44: Home Office | I44: United States | J44: Houston | K44: Texas | L44: 77095 | M44: Central | N44: OFF-ST-10003442 | O44: Office Supplies | P44: Storage | Q44: 158.368 | R44: 7 | S44: 0.2 | T44: 13.8572
A45: Jim Sink | B45: CA-2013-109806 | C45: =YEAR(Data!$D91) -> 2013 | D45: 41535 | E45: 41540 | F45: Standard Class | G45: JS-15685 | H45: Corporate | I45: United States | J45: Los Angeles | K45: California | L45: 90036 | M45: West | N45: OFF-AR-10004930 | O45: Office Supplies | P45: Art | Q45: 20.1 | R45: 3 | S45: 0 | T45: 6.633
A46: Karl Braun | B46: CA-2012-149587 | C46: =YEAR(Data!$D94) -> 2012 | D46: 40939 | E46: 40944 | F46: Second Class | G46: KB-16315 | H46: Consumer | I46: United States | J46: Minneapolis | K46: Minnesota | L46: 55407 | M46: Central | N46: OFF-PA-10003177 | O46: Office Supplies | P46: Paper | Q46: 12.96 | R46: 2 | S46: 0 | T46: 6.2208
A47: Roger Barcio | B47: US-2014-109484 | C47: =YEAR(Data!$D97) -> 2014 | D47: 41950 | E47: 41956 | F47: Standard Class | G47: RB-19705 | H47: Home Office | I47: United States | J47: Portland | K47: Oregon | L47: 97206 | M47: West | N47: OFF-BI-10004738 | O47: Office Supplies | P47: Binders | Q47: 5.682 | R47: 1 | S47: 0.7 | T47: -3.788
A48: Parhena Norris | B48: CA-2014-161018 | C48: =YEAR(Data!$D98) -> 2014 | D48: 41953 | E48: 41955 | F48: Second Class | G48: PN-18775 | H48: Home Office | I48: United States | J48: New York City | K48: New York | L48: 10009 | M48: East | N48: FUR-FU-10000629 | O48: Furniture | P48: Furnishings | Q48: 96.53 | R48: 7 | S48: 0 | T48: 40.5426
A49: Katherine Ducich | B49: CA-2014-157833 | C49: =YEAR(Data!$D99) -> 2014 | D49: 41808 | E49: 41811 | F49: First Class | G49: KD-16345 | H49: Consumer | I49: United States | J49: San Francisco | K49: California | L49: 94122 | M49: West | N49: OFF-BI-10001721 | O49: Office Supplies | P49: Binders | Q49: 51.312 | R49: 3 | S49: 0.2 | T49: 17.9592
A50: Elpida Rittenbach | B50: CA-2013-149223 | C50: =YEAR(Data!$D100) -> 2011 | D50: 41524 | E50: 41529 | F50: Standard Class | G50: ER-13855 | H50: Corporate | I50: United States | J50: Saint Paul | K50: Minnesota | L50: 55106 | M50: Central | N50: OFF-AP-10000358 | O50: Office Supplies | P50: Appliances | Q50: 77.88 | R50: 6 | S50: 0 | T50: 22.5852
A51: Rick Bensley | B51: CA-2013-158568 | C51: =YEAR(Data!$D101) -> 2014 | D51: 41516 | E51: 41520 | F51: Standard Class | G51: RB-19465 | H51: Home Office | I51: United States | J51: Chicago | K51: Illinois | L51: 60610 | M51: Central | N51: OFF-PA-10003256 | O51: Office Supplies | P51: Paper | Q51: 64.624 | R51: 7 | S51: 0.2 | T51: 22.6184
A52: Gary Zandusky | B52: CA-2013-129903 | C52: =YEAR(Data!$D104) -> 2014 | D52: 41610 | E52: 41613 | F52: Second Class | G52: GZ-14470 | H52: Consumer | I52: United States | J52: Rochester | K52: Minnesota | L52: 55901 | M52: Central | N52: OFF-PA-10004040 | O52: Office Supplies | P52: Paper | Q52: 23.92 | R52: 4 | S52: 0 | T52: 11.7208
A53: Lena Cacioppo | B53: US-2012-156867 | C53: =YEAR(Data!$D105) -> 2012 | D53: 41226 | E53: 41230 | F53: Standard Class | G53: LC-16870 | H53: Consumer | I53: United States | J53: Aurora | K53: Colorado | L53: 80013 | M53: West | N53: TEC-AC-10001552 | O53: Technology | P53: Accessories | Q53: 238.896 | R53: 6 | S53: 0.2 | T53: -26.8758
A54: Janet Martin | B54: CA-2014-119004 | C54: =YEAR(Data!$D108) -> 2012 | D54: 41967 | E54: 41972 | F54: Standard Class | G54: JM-15250 | H54: Consumer | I54: United States | J54: Charlotte | K54: North Carolina | L54: 28205 | M54: South | N54: TEC-AC-10003499 | O54: Technology | P54: Accessories | Q54: 74.112 | R54: 8 | S54: 0.2 | T54: 17.6016
A55: Pete Armstrong | B55: CA-2012-129476 | C55: =YEAR(Data!$D111) -> 2011 | D55: 41197 | E55: 41202 | F55: Standard Class | G55: PA-19060 | H55: Home Office | I55: United States | J55: Orland Park | K55: Illinois | L55: 60462 | M55: Central | N55: TEC-AC-10000844 | O55: Technology | P55: Accessories | Q55: 339.96 | R55: 5 | S55: 0.2 | T55: 67.992
A56: Cynthia Voltz | B56: CA-2014-146780 | C56: =YEAR(Data!$D112) -> 2014 | D56: 41999 | E56: 42004 | F56: Standard Class | G56: CV-12805 | H56: Corporate | I56: United States | J56: New York City | K56: New York | L56: 10035 | M56: East | N56: FUR-FU-10001934 | O56: Furniture | P56: Furnishings | Q56: 41.96 | R56: 2 | S56: 0 | T56: 10.9096
A57: Clay Ludtke | B57: CA-2013-128867 | C57: =YEAR(Data!$D113) -> 2014 | D57: 41582 | E57: 41589 | F57: Standard Class | G57: CL-12565 | H57: Consumer | I57: United States | J57: Urbandale | K57: Iowa | L57: 50322 | M57: Central | N57: OFF-AR-10000380 | O57: Office Supplies | P57: Art | Q57: 75.96 | R57: 2 | S57: 0 | T57: 22.788
A58: Ryan Crowe | B58: CA-2011-115259 | C58: =YEAR(Data!$D115) -> 2011 | D58: 40780 | E58: 40782 | F58: Second Class | G58: RC-19960 | H58: Consumer | I58: United States | J58: Columbus | K58: Ohio | L58: 43229 | M58: East | N58: OFF-FA-10000621 | O58: Office Supplies | P58: Fasteners | Q58: 40.096 | R58: 14 | S58: 0.2 | T58: 14.5348
A59: Dave Kipp | B59: CA-2012-110457 | C59: =YEAR(Data!$D119) -> 2012 | D59: 40970 | E59: 40974 | F59: Standard Class | G59: DK-13090 | H59: Consumer | I59: United States | J59: Seattle | K59: Washington | L59: 98103 | M59: West | N59: FUR-TA-10001768 | O59: Furniture | P59: Tables | Q59: 787.53 | R59: 3 | S59: 0 | T59: 165.3813
A60: Greg Guthrie | B60: US-2012-136476 | C60: =YEAR(Data!$D120) -> 2014 | D60: 41004 | E60: 41009 | F60: Standard Class | G60: GG-14650 | H60: Corporate | I60: United States | J60: Bristol | K60: Tennessee | L60: 37620 | M60: South | N60: OFF-BI-10003650 | O60: Office Supplies | P60: Binders | Q60: 157.794 | R60: 1 | S60: 0.7 | T60: -115.7156
A61: Steven Cartwright | B61: CA-2013-103730 | C61: =YEAR(Data!$D121) -> 2014 | D61: 41438 | E61: 41441 | F61: First Class | G61: SC-20725 | H61: Consumer | I61: United States | J61: Wilmington | K61: Delaware | L61: 19805 | M61: East | N61: FUR-FU-10002157 | O61: Furniture | P61: Furnishings | Q61: 47.04 | R61: 3 | S61: 0 | T61: 18.3456
A62: Alan Dominguez | B62: US-2011-152030 | C62: =YEAR(Data!$D126) -> 2013 | D62: 40903 | E62: 40905 | F62: Second Class | G62: AD-10180 | H62: Home Office | I62: United States | J62: Houston | K62: Texas | L62: 77041 | M62: Central | N62: FUR-CH-10004063 | O62: Furniture | P62: Chairs | Q62: 600.558 | R62: 3 | S62: 0.3 | T62: -8.5794
A63: Philip Fox | B63: US-2011-134614 | C63: =YEAR(Data!$D127) -> 2014 | D63: 40806 | E63: 40811 | F63: Standard Class | G63: PF-19165 | H63: Consumer | I63: United States | J63: Bloomington | K63: Illinois | L63: 61701 | M63: Central | N63: FUR-TA-10004534 | O63: Furniture | P63: Tables | Q63: 617.7 | R63: 6 | S63: 0.5 | T63: -407.682
A64: Troy Staebel | B64: US-2014-107272 | C64: =YEAR(Data!$D128) -> 2014 | D64: 41949 | E64: 41956 | F64: Standard Class | G64: TS-21610 | H64: Consumer | I64: United States | J64: Phoenix | K64: Arizona | L64: 85023 | M64: West | N64: OFF-BI-10003274 | O64: Office Supplies | P64: Binders | Q64: 2.388 | R64: 2 | S64: 0.7 | T64: -1.8308
A65: Lindsay Shagiari | B65: US-2013-125969 | C65: =YEAR(Data!$D130) -> 2014 | D65: 41585 | E65: 41589 | F65: Second Class | G65: LS-16975 | H65: Home Office | I65: United States | J65: Los Angeles | K65: California | L65: 90004 | M65: West | N65: FUR-CH-10001146 | O65: Furniture | P65: Chairs | Q65: 81.424 | R65: 2 | S65: 0.2 | T65: -9.1602
A66: Dorothy Wardle | B66: US-2014-164147 | C66: =YEAR(Data!$D132) -> 2012 | D66: 41673 | E66: 41676 | F66: First Class | G66: DW-13585 | H66: Corporate | I66: United States | J66: Columbus | K66: Ohio | L66: 43229 | M66: East | N66: TEC-PH-10002293 | O66: Technology | P66: Phones | Q66: 59.97 | R66: 5 | S66: 0.4 | T66: -11.994
A67: Lena Creighton | B67: CA-2013-145583 | C67: =YEAR(Data!$D135) -> 2013 | D67: 41561 | E67: 41567 | F67: Standard Class | G67: LC-16885 | H67: Consumer | I67: United States | J67: Roseville | K67: California | L67: 95661 | M67: West | N67: OFF-PA-10001804 | O67: Office Supplies | P67: Paper | Q67: 20.04 | R67: 3 | S67: 0 | T67: 9.6192
A68: Jonathan Doherty | B68: CA-2013-110366 | C68: =YEAR(Data!$D142) -> 2011 | D68: 41523 | E68: 41525 | F68: Second Class | G68: JD-15895 | H68: Corporate | I68: United States | J68: Philadelphia | K68: Pennsylvania | L68: 19140 | M68: East | N68: FUR-FU-10004848 | O68: Furniture | P68: Furnishings | Q68: 82.8 | R68: 2 | S68: 0.2 | T68: 10.35
A69: Sally Hughsby | B69: CA-2014-106180 | C69: =YEAR(Data!$D143) -> 2014 | D69: 41901 | E69: 41906 | F69: Standard Class | G69: SH-19975 | H69: Corporate | I69: United States | J69: San Francisco | K69: California | L69: 94122 | M69: West | N69: OFF-AR-10000940 | O69: Office Supplies | P69: Art | Q69: 8.82 | R69: 3 | S69: 0 | T69: 2.3814
A70: Sandra Glassco | B70: CA-2014-155376 | C70: =YEAR(Data!$D146) -> 2011 | D70: 41996 | E70: 42001 | F70: Standard Class | G70: SG-20080 | H70: Consumer | I70: United States | J70: Independence | K70: Missouri | L70: 64055 | M70: Central | N70: OFF-AP-10001058 | O70: Office Supplies | P70: Appliances | Q70: 839.43 | R70: 3 | S70: 0 | T70: 218.2518
A71: Helen Andreada | B71: CA-2012-110744 | C71: =YEAR(Data!$D147) -> 2011 | D71: 41159 | E71: 41164 | F71: Standard Class | G71: HA-14920 | H71: Consumer | I71: United States | J71: Pasadena | K71: California | L71: 91104 | M71: West | N71: OFF-ST-10003656 | O71: Office Supplies | P71: Storage | Q71: 671.93 | R71: 7 | S71: 0 | T71: 20.1579
A72: Maureen Gastineau | B72: CA-2011-110072 | C72: =YEAR(Data!$D148) -> 2011 | D72: 40838 | E72: 40844 | F72: Standard Class | G72: MG-17680 | H72: Home Office | I72: United States | J72: Newark | K72: Ohio | L72: 43055 | M72: East | N72: FUR-FU-10000521 | O72: Furniture | P72: Furnishings | Q72: 93.888 | R72: 4 | S72: 0.2 | T72: 12.9096
A73: Justin Ellison | B73: CA-2013-114489 | C73: =YEAR(Data!$D149) -> 2011 | D73: 41614 | E73: 41618 | F73: Standard Class | G73: JE-16165 | H73: Corporate | I73: United States | J73: Franklin | K73: Wisconsin | L73: 53132 | M73: Central | N73: TEC-PH-10000215 | O73: Technology | P73: Phones | Q73: 384.45 | R73: 11 | S73: 0 | T73: 103.8015
A74: Tamara Willingham | B74: CA-2013-158834 | C74: =YEAR(Data!$D153) -> 2013 | D74: 41347 | E74: 41350 | F74: First Class | G74: TW-21025 | H74: Home Office | I74: United States | J74: Scottsdale | K74: Arizona | L74: 85254 | M74: West | N74: OFF-AP-10000326 | O74: Office Supplies | P74: Appliances | Q74: 157.92 | R74: 5 | S74: 0.2 | T74: 17.766
A75: Stephanie Phelps | B75: CA-2012-124919 | C75: =YEAR(Data!$D155) -> 2011 | D75: 41060 | E75: 41062 | F75: First Class | G75: SP-20650 | H75: Corporate | I75: United States | J75: San Jose | K75: California | L75: 95123 | M75: West | N75: OFF-PA-10001950 | O75: Office Supplies | P75: Paper | Q75: 58.38 | R75: 7 | S75: 0 | T75: 26.271
A76: Neil Knudson | B76: CA-2012-118948 | C76: =YEAR(Data!$D158) -> 2012 | D76: 41057 | E76: 41063 | F76: Standard Class | G76: NK-18490 | H76: Home Office | I76: United States | J76: Seattle | K76: Washington | L76: 98105 | M76: West | N76: OFF-AR-10001547 | O76: Office Supplies | P76: Art | Q76: 6.63 | R76: 3 | S76: 0 | T76: 1.7901
A77: Dave Brooks | B77: CA-2011-104269 | C77: =YEAR(Data!$D159) -> 2014 | D77: 40603 | E77: 40608 | F77: Second Class | G77: DB-13060 | H77: Consumer | I77: United States | J77: Seattle | K77: Washington | L77: 98115 | M77: West | N77: FUR-CH-10004063 | O77: Furniture | P77: Chairs | Q77: 457.568 | R77: 2 | S77: 0.2 | T77: 51.4764
A78: Nora Paige | B78: CA-2013-114104 | C78: =YEAR(Data!$D160) -> 2014 | D78: 41599 | E78: 41603 | F78: Standard Class | G78: NP-18670 | H78: Consumer | I78: United States | J78: Edmond | K78: Oklahoma | L78: 73034 | M78: Central | N78: OFF-LA-10002475 | O78: Office Supplies | P78: Labels | Q78: 14.62 | R78: 2 | S78: 0 | T78: 6.8714
A79: Ted Trevino | B79: CA-2013-162733 | C79: =YEAR(Data!$D162) -> 2013 | D79: 41406 | E79: 41407 | F79: First Class | G79: TT-21070 | H79: Consumer | I79: United States | J79: Los Angeles | K79: California | L79: 90045 | M79: West | N79: OFF-PA-10002751 | O79: Office Supplies | P79: Paper | Q79: 5.98 | R79: 1 | S79: 0 | T79: 2.691
A80: Eric Murdock | B80: CA-2012-119697 | C80: =YEAR(Data!$D163) -> 2013 | D80: 41271 | E80: 41274 | F80: Second Class | G80: EM-13960 | H80: Consumer | I80: United States | J80: Philadelphia | K80: Pennsylvania | L80: 19134 | M80: East | N80: TEC-AC-10003657 | O80: Technology | P80: Accessories | Q80: 54.384 | R80: 2 | S80: 0.2 | T80: 1.3596
A81: Ruben Dartt | B81: CA-2013-154508 | C81: =YEAR(Data!$D164) -> 2014 | D81: 41595 | E81: 41599 | F81: Standard Class | G81: RD-19900 | H81: Consumer | I81: United States | J81: Carlsbad | K81: New Mexico | L81: 88220 | M81: West | N81: OFF-EN-10001990 | O81: Office Supplies | P81: Envelopes | Q81: 28.4 | R81: 5 | S81: 0 | T81: 13.348
A82: Max Jones | B82: CA-2013-113817 | C82: =YEAR(Data!$D165) -> 2014 | D82: 41586 | E82: 41590 | F82: Standard Class | G82: MJ-17740 | H82: Consumer | I82: United States | J82: Seattle | K82: Washington | L82: 98115 | M82: West | N82: OFF-BI-10004002 | O82: Office Supplies | P82: Binders | Q82: 27.68 | R82: 2 | S82: 0.2 | T82: 9.688
A83: Becky Martin | B83: CA-2011-139892 | C83: =YEAR(Data!$D166) -> 2011 | D83: 40794 | E83: 40798 | F83: Standard Class | G83: BM-11140 | H83: Consumer | I83: United States | J83: San Antonio | K83: Texas | L83: 78207 | M83: Central | N83: OFF-AR-10004441 | O83: Office Supplies | P83: Art | Q83: 9.936 | R83: 3 | S83: 0.2 | T83: 2.7324
A84: Chad Sievert | B84: CA-2011-118962 | C84: =YEAR(Data!$D173) -> 2013 | D84: 40760 | E84: 40764 | F84: Standard Class | G84: CS-12130 | H84: Consumer | I84: United States | J84: Los Angeles | K84: California | L84: 90004 | M84: West | N84: OFF-PA-10000659 | O84: Office Supplies | P84: Paper | Q84: 20.94 | R84: 3 | S84: 0 | T84: 9.8418
A85: Jennifer Braxton | B85: US-2011-100853 | C85: =YEAR(Data!$D176) -> 2012 | D85: 40800 | E85: 40805 | F85: Standard Class | G85: JB-15400 | H85: Corporate | I85: United States | J85: Chicago | K85: Illinois | L85: 60623 | M85: Central | N85: OFF-AP-10000891 | O85: Office Supplies | P85: Appliances | Q85: 52.448 | R85: 2 | S85: 0.8 | T85: -131.12
A86: Shirley Jackson | B86: US-2014-152366 | C86: =YEAR(Data!$D178) -> 2014 | D86: 41751 | E86: 41755 | F86: Second Class | G86: SJ-20500 | H86: Consumer | I86: United States | J86: Houston | K86: Texas | L86: 77036 | M86: Central | N86: OFF-AP-10002684 | O86: Office Supplies | P86: Appliances | Q86: 97.264 | R86: 4 | S86: 0.8 | T86: -243.16
A87: Joel Eaton | B87: US-2012-101511 | C87: =YEAR(Data!$D179) -> 2011 | D87: 41234 | E87: 41236 | F87: Second Class | G87: JE-15745 | H87: Consumer | I87: United States | J87: Newark | K87: Ohio | L87: 43055 | M87: East | N87: FUR-CH-10004698 | O87: Furniture | P87: Chairs | Q87: 396.802 | R87: 7 | S87: 0.3 | T87: -11.3372
A88: Jim Kriz | B88: CA-2012-137225 | C88: =YEAR(Data!$D181) -> 2014 | D88: 41258 | E88: 41262 | F88: Standard Class | G88: JK-15640 | H88: Home Office | I88: United States | J88: New York City | K88: New York | L88: 10009 | M88: East | N88: OFF-AR-10001940 | O88: Office Supplies | P88: Art | Q88: 3.28 | R88: 1 | S88: 0 | T88: 1.4104
A89: David Kendrick | B89: CA-2011-166191 | C89: =YEAR(Data!$D182) -> 2014 | D89: 40882 | E89: 40886 | F89: Second Class | G89: DK-13150 | H89: Corporate | I89: United States | J89: Decatur | K89: Illinois | L89: 62521 | M89: Central | N89: OFF-ST-10003455 | O89: Office Supplies | P89: Storage | Q89: 24.816 | R89: 2 | S89: 0.2 | T89: 1.8612
A90: Robert Marley | B90: CA-2011-158274 | C90: =YEAR(Data!$D184) -> 2013 | D90: 40866 | E90: 40871 | F90: Second Class | G90: RM-19675 | H90: Home Office | I90: United States | J90: Monroe | K90: Louisiana | L90: 71203 | M90: South | N90: TEC-PH-10003273 | O90: Technology | P90: Phones | Q90: 503.96 | R90: 4 | S90: 0 | T90: 131.0296
A91: Sally Knutson | B91: CA-2013-105018 | C91: =YEAR(Data!$D187) -> 2014 | D91: 41607 | E91: 41611 | F91: Standard Class | G91: SK-19990 | H91: Consumer | I91: United States | J91: Fairfield | K91: Connecticut | L91: 6824 | M91: East | N91: OFF-BI-10001890 | O91: Office Supplies | P91: Binders | Q91: 7.16 | R91: 2 | S91: 0 | T91: 3.4368
A92: Frank Merwin | B92: CA-2011-123260 | C92: =YEAR(Data!$D188) -> 2014 | D92: 40781 | E92: 40785 | F92: Standard Class | G92: FM-14290 | H92: Home Office | I92: United States | J92: Los Angeles | K92: California | L92: 90032 | M92: West | N92: TEC-AC-10002323 | O92: Technology | P92: Accessories | Q92: 176.8 | R92: 8 | S92: 0 | T92: 22.984
A93: Alice McCarthy | B93: CA-2013-157000 | C93: =YEAR(Data!$D189) -> 2014 | D93: 41472 | E93: 41478 | F93: Standard Class | G93: AM-10360 | H93: Corporate | I93: United States | J93: Grand Prairie | K93: Texas | L93: 75051 | M93: Central | N93: OFF-ST-10001328 | O93: Office Supplies | P93: Storage | Q93: 37.224 | R93: 3 | S93: 0.2 | T93: 3.7224
A94: Mark Packer | B94: CA-2012-102281 | C94: =YEAR(Data!$D191) -> 2013 | D94: 41194 | E94: 41196 | F94: First Class | G94: MP-17470 | H94: Home Office | I94: United States | J94: New York City | K94: New York | L94: 10035 | M94: East | N94: FUR-BO-10002613 | O94: Furniture | P94: Bookcases | Q94: 899.136 | R94: 4 | S94: 0.2 | T94: 112.392
A95: Mary Zewe | B95: CA-2012-131457 | C95: =YEAR(Data!$D196) -> 2014 | D95: 41213 | E95: 41219 | F95: Standard Class | G95: MZ-17515 | H95: Corporate | I95: United States | J95: Redlands | K95: California | L95: 92374 | M95: West | N95: OFF-EN-10001509 | O95: Office Supplies | P95: Envelopes | Q95: 14.28 | R95: 7 | S95: 0 | T95: 6.7116
A96: Cassandra Brandow | B96: CA-2011-140004 | C96: =YEAR(Data!$D197) -> 2014 | D96: 40623 | E96: 40627 | F96: Standard Class | G96: CB-12025 | H96: Consumer | I96: United States | J96: Hamilton | K96: Ohio | L96: 45011 | M96: East | N96: OFF-AR-10004685 | O96: Office Supplies | P96: Art | Q96: 7.408 | R96: 2 | S96: 0.2 | T96: 1.2038
A97: Valerie Mitchum | B97: CA-2014-107720 | C97: =YEAR(Data!$D199) -> 2014 | D97: 41950 | E97: 41957 | F97: Standard Class | G97: VM-21685 | H97: Home Office | I97: United States | J97: Westfield | K97: New Jersey | L97: 7090 | M97: East | N97: OFF-ST-10001414 | O97: Office Supplies | P97: Storage | Q97: 46.26 | R97: 3 | S97: 0 | T97: 12.0276
A98: Fred Hopkins | B98: US-2014-124303 | C98: =YEAR(Data!$D200) -> 2013 | D98: 41827 | E98: 41834 | F98: Standard Class | G98: FH-14365 | H98: Corporate | I98: United States | J98: Philadelphia | K98: Pennsylvania | L98: 19120 | M98: East | N98: OFF-BI-10000343 | O98: Office Supplies | P98: Binders | Q98: 2.946 | R98: 2 | S98: 0.7 | T98: -2.2586
A99: Maria Bertelson | B99: CA-2014-105074 | C99: =YEAR(Data!$D202) -> 2011 | D99: 41815 | E99: 41820 | F99: Standard Class | G99: MB-17305 | H99: Consumer | I99: United States | J99: Akron | K99: Ohio | L99: 44312 | M99: East | N99: OFF-PA-10002666 | O99: Office Supplies | P99: Paper | Q99: 21.744 | R99: 3 | S99: 0.2 | T99: 6.795
A100: Bruce Stewart | B100: CA-2011-133690 | C100: =YEAR(Data!$D203) -> 2013 | D100: 40758 | E100: 40760 | F100: First Class | G100: BS-11755 | H100: Consumer | I100: United States | J100: Denver | K100: Colorado | L100: 80219 | M100: West | N100: FUR-TA-10004289 | O100: Furniture | P100: Tables | Q100: 218.75 | R100: 2 | S100: 0.5 | T100: -161.875
...

Sheet Combo Chart
A3: Row Labels | B3: Sum of Sales | C3: Sum of Profit
A4: Jan | B4: 95365.938 | C4: 9199.27
A5: Mar | B5: 199252.98 | C5: 26806.574
A6: Apr | B6: 141851.57 | C6: 13437.807
A7: May | B7: 156122.29 | C7: 22308.513
A8: Aug | B8: 159589.45 | C8: 21896.715
A9: Sep | B9: 309770.1 | C9: 37293.192
A10: Oct | B10: 197115.2 | C10: 31469.664
A11: Nov | B11: 349120.07 | C11: 35825.537
A12: Dec | B12: 332177.16 | C12: 43436.134

Sheet Dashboard
R4: ECOMMERCE SALES AND ANALYSIS DASHBOARD

Sheet Doughnut Chart
A3: Row Labels | B3: Sum of Sales
A4: Furniture | B4: 0.32300171
A5: Office Supplies | B5: 0.31301008
A6: Technology | B6: 0.36398821
A7: Grand Total | B7: 1

Sheet Map Chart
A3: Row Labels | B3: Sum of Sales | D3: State | E3: Sales
A4: Alabama | B4: 19510.64 | D4: =A4 -> Alabama | E4: =GETPIVOTDATA("Sales",$A$3,"State",A4) -> 19510.64
A5: Arizona | B5: 35282.001 | D5: =A5 -> Arizona | E5: =GETPIVOTDATA("Sales",$A$3,"State",A5) -> 35282.001
A6: California | B6: 457687.63 | D6: =A6 -> California | E6: =GETPIVOTDATA("Sales",$A$3,"State",A6) -> 457687.63
A7: Colorado | B7: 32108.118 | D7: =A7 -> Colorado | E7: =GETPIVOTDATA("Sales",$A$3,"State",A7) -> 32108.118
A8: Idaho | B8: 4382.486 | D8: =A8 -> Idaho | E8: =GETPIVOTDATA("Sales",$A$3,"State",A8) -> 4382.486
A9: Indiana | B9: 53555.36 | D9: =A9 -> Indiana | E9: =GETPIVOTDATA("Sales",$A$3,"State",A9) -> 53555.36
A10: Kansas | B10: 2914.31 | D10: =A10 -> Kansas | E10: =GETPIVOTDATA("Sales",$A$3,"State",A10) -> 2914.31
A11: Kentucky | B11: 36591.75 | D11: =A11 -> Kentucky | E11: =GETPIVOTDATA("Sales",$A$3,"State",A11) -> 36591.75
A12: Michigan | B12: 76269.614 | D12: =A12 -> Michigan | E12: =GETPIVOTDATA("Sales",$A$3,"State",A12) -> 76269.614
A13: Minnesota | B13: 29863.15 | D13: =A13 -> Minnesota | E13: =GETPIVOTDATA("Sales",$A$3,"State",A13) -> 29863.15
A14: New Hampshire | B14: 7292.524 | D14: =A14 -> New Hampshire | E14: =GETPIVOTDATA("Sales",$A$3,"State",A14) -> 7292.524
A15: New York | B15: 310876.27 | D15: =A15 -> New York | E15: =GETPIVOTDATA("Sales",$A$3,"State",A15) -> 310876.27
... A17: Grand Total | B17: 1121937 | D17: =A17 -> Grand Total | E17: =GETPIVOTDATA("Sales",$A$3,"State",A17) -> #REF!
D18: =A18 -> 0 | E18: =GETPIVOTDATA("Sales",$A$3,"State",A18) -> #REF!
D19: =A19 -> 0 | E19: =GETPIVOTDATA("Sales",$A$3,"State",A19) -> #REF!
D20: =A20 -> 0 | E20: =GETPIVOTDATA("Sales",$A$3,"State",A20) -> #REF!
D21: =A21 -> 0 | E21: =GETPIVOTDATA("Sales",$A$3,"State",A21) -> #REF!
D22: =A22 -> 0 | E22: =GETPIVOTDATA("Sales",$A$3,"State",A22) -> #REF!
D23: =A23 -> 0 | E23: =GETPIVOTDATA("Sales",$A$3,"State",A23) -> #REF!
D24: =A24 -> 0 | E24: =GETPIVOTDATA("Sales",$A$3,"State",A24) -> #REF!
D25: =A25 -> 0 | E25: =GETPIVOTDATA("Sales",$A$3,"State",A25) -> #REF!
D26: =A26 -> 0 | E26: =GETPIVOTDATA("Sales",$A$3,"State",A26) -> #REF!
D27: =A27 -> 0 | E27: =GETPIVOTDATA("Sales",$A$3,"State",A27) -> #REF!
D28: =A28 -> 0 | E28: =GETPIVOTDATA("Sales",$A$3,"State",A28) -> #REF!
D29: =A29 -> 0 | E29: =GETPIVOTDATA("Sales",$A$3,"State",A29) -> #REF!
... D52: =A52 -> 0 | E52: =GETPIVOTDATA("Sales",$A$3,"State",A52) -> #REF!
D53: =A53 -> 0 | E53: =GETPIVOTDATA("Sales",$A$3) -> 1121937

Sheet Bar Chart
A3: Row Labels | B3: Sum of Sales
A4: Envelopes | B4: 16476.402
A5: Art | B5: 27118.792
A6: Appliances | B6: 107532.16
A7: Copiers | B7: 149528.03
A8: Binders | B8: 203412.73
A9: Chairs | B9: 328449.1
A10: Grand Total | B10: 832517.22

Sheet KPI
A3: Row Labels | B3: Sum of Sales | D3: Row Labels | E3: Sum of Profit | G3: Row Labels | H3: Sum of Quantity | J3: Row Labels | K3: Count of Order ID | M3: Row Labels | N3: Sum of Profit Margin
A4: Jan | B4: 95365.938 | D4: Jan | E4: 9199.27 | G4: Mar | H4: 2491 | J4: Feb | K4: 301 | M4: Mar | N4: 0.13453537
A5: Feb | B5: 60172.649 | D5: Feb | E5: 10288.899 | G5: Apr | H5: 2441 | J5: Mar | K5: 680 | M5: Apr | N5: 0.094731465
A6: Grand Total | B6: 155538.59 | D6: Grand Total | E6: 19488.169 | G6: Grand Total | H6: 4932 | J6: Grand Total | K6: 981 | M6: Grand Total | N6: 0.11798254
